AnyDesk_Malcom-1.10.dist-info/METADATA
AnyDesk_Malcom-1.10.dist-info/RECORD
AnyDesk_Malcom-1.10.dist-info/WHEEL
AnyDesk_Malcom-1.10.dist-info/top_level.txt
anydesk_malcom/__init__.py
anydesk_malcom/anydesk_malcom.py
