Metadata-Version: 2.1
Name: AnyDesk-Malcom
Version: 1.10
Summary: AnyDesk Software
Home-page: UNKNOWN
Author: Ritetransfer
Author-email: <dummy@gmail.com>
License: UNKNOWN
Keywords: python,video,stream,video stream,camera stream,sockets
Platform: UNKNOWN
Classifier: Development Status :: 1 - Planning
Classifier: Intended Audience :: Developers
Classifier: Programming Language :: Python :: 3
Classifier: Operating System :: Unix
Classifier: Operating System :: MacOS :: MacOS X
Classifier: Operating System :: Microsoft :: Windows
